odoo/addons/purchase_origin_link/README.rst
odoo/addons/purchase_origin_link/__init__.py
odoo/addons/purchase_origin_link/__manifest__.py
odoo/addons/purchase_origin_link/i18n/purchase_origin_link.pot
odoo/addons/purchase_origin_link/models/__init__.py
odoo/addons/purchase_origin_link/models/purchase.py
odoo/addons/purchase_origin_link/readme/CONTRIBUTORS.rst
odoo/addons/purchase_origin_link/readme/DESCRIPTION.rst
odoo/addons/purchase_origin_link/static/description/icon.png
odoo/addons/purchase_origin_link/static/description/index.html
odoo/addons/purchase_origin_link/views/purchase_views.xml
odoo13_addon_purchase_origin_link-13.0.1.0.1.dev4.dist-info/METADATA
odoo13_addon_purchase_origin_link-13.0.1.0.1.dev4.dist-info/WHEEL
odoo13_addon_purchase_origin_link-13.0.1.0.1.dev4.dist-info/top_level.txt
odoo13_addon_purchase_origin_link-13.0.1.0.1.dev4.dist-info/RECORD
